.gitignore
COPYING
README.asciidoc
README.txt
header
setup.py
terebi/__init__.py
terebi/mpv.py
terebi/promise.py
terebi.egg-info/PKG-INFO
terebi.egg-info/SOURCES.txt
terebi.egg-info/dependency_links.txt
terebi.egg-info/top_level.txt