Metadata-Version: 1.1
Name: terebi
Version: 0.1.1
Summary: a python interface to mpv
Home-page: https://github.com/slowpoketail/terebi
Author: slowpoke
Author-email: mail+pypi@slowpoke.io
License: ANTI-LICENSE
Platform: UNKNOWN
Classifier: Development Status :: 3 - Alpha
Classifier: Intended Audience :: Developers
Classifier: License :: Public Domain
Classifier: Programming Language :: Python :: 3 :: Only
Classifier: Operating System :: POSIX :: Linux
